setup.py
slither/__init__.py
slither/snakey.png
slither.egg-info/PKG-INFO
slither.egg-info/SOURCES.txt
slither.egg-info/dependency_links.txt
slither.egg-info/top_level.txt
slither/examples/SOS.png
slither/examples/SoExcited.png
slither/examples/__init__.py
slither/examples/basicTest.py
slither/examples/bg2.png
slither/examples/bgTest.py
slither/examples/boom.wav
slither/examples/circle.png
slither/examples/imageBounceTest.py
slither/examples/snakey.png
slither/examples/soundtest.py
slither/examples/turnAndMove.py
slither/examples/zindextest.py