Metadata-Version: 1.1
Name: slither
Version: 0.2.1
Summary: A Python module that uses PyGame to bring Scratch-like features to Python
Home-page: https://github.com/PySlither/Slither
Author: Tymewalk
Author-email: none
License: MIT
Keywords: scratch pygame
Platform: UNKNOWN
Classifier: Development Status :: 3 - Alpha
Classifier: Intended Audience :: Other Audience
Classifier: Topic :: Games/Entertainment
Classifier: License :: OSI Approved :: MIT License
Classifier: Programming Language :: Python :: 3
Classifier: Programming Language :: Python :: 3.2
Classifier: Programming Language :: Python :: 3.3
Classifier: Programming Language :: Python :: 3.4
Classifier: Programming Language :: Python :: 3.5
